spicerack/__init__.py
spicerack/_cookbook.py
spicerack/_log.py
spicerack/_menu.py
spicerack/_module_api.py
spicerack/administrative.py
spicerack/alerting.py
spicerack/alertmanager.py
spicerack/apiclient.py
spicerack/apt.py
spicerack/confctl.py
spicerack/constants.py
spicerack/cookbook.py
spicerack/dbctl.py
spicerack/debmonitor.py
spicerack/decorators.py
spicerack/dhcp.py
spicerack/dnsdisc.py
spicerack/elasticsearch_cluster.py
spicerack/exceptions.py
spicerack/ganeti.py
spicerack/hosts.py
spicerack/icinga.py
spicerack/interactive.py
spicerack/ipmi.py
spicerack/k8s.py
spicerack/kafka.py
spicerack/locking.py
spicerack/mediawiki.py
spicerack/mysql.py
spicerack/netbox.py
spicerack/orchestrator.py
spicerack/peeringdb.py
spicerack/puppet.py
spicerack/py.typed
spicerack/redfish.py
spicerack/redis_cluster.py
spicerack/remote.py
spicerack/reposync.py
spicerack/service.py
spicerack/typing.py
spicerack/toolforge/__init__.py
spicerack/toolforge/etcdctl.py
wikimedia_spicerack-12.2.0.dist-info/licenses/LICENSE
wikimedia_spicerack-12.2.0.dist-info/METADATA
wikimedia_spicerack-12.2.0.dist-info/WHEEL
wikimedia_spicerack-12.2.0.dist-info/entry_points.txt
wikimedia_spicerack-12.2.0.dist-info/top_level.txt
wikimedia_spicerack-12.2.0.dist-info/RECORD
